src/main.py
src/models.py
src/tasks.py
stt_bench-0.1.0.dist-info/licenses/LICENSE
stt_bench-0.1.0.dist-info/METADATA
stt_bench-0.1.0.dist-info/WHEEL
stt_bench-0.1.0.dist-info/entry_points.txt
stt_bench-0.1.0.dist-info/top_level.txt
stt_bench-0.1.0.dist-info/RECORD
