Metadata-Version: 2.4
Name: stt-bench
Version: 0.1.0
Summary: A benchmark tool for Speech-to-Text models.
Author-email: Gautam Jha <gautam@kalpalabs.ai>
License: MIT License
Requires-Python: ==3.12.3
License-File: LICENSE
Requires-Dist: datasets==4.0.0
Requires-Dist: hf-transfer==0.1.9
Requires-Dist: librosa>=0.11.0
Requires-Dist: torch==2.7.0
Requires-Dist: torchaudio==2.7.0
Requires-Dist: torchcodec==0.5.0
Requires-Dist: transformers>=4.52.4
Requires-Dist: jiwer>=4.0.0
Requires-Dist: openai>=2.6.0
Requires-Dist: onnxruntime>=1.23.2
Requires-Dist: typer>=0.20.0
Requires-Dist: deepgram-sdk>=5.2.0
Dynamic: license-file
